audiostretchy/__init__.py
audiostretchy/__main__.py
audiostretchy/stretch.py
audiostretchy/interface/tdhs.py
audiostretchy/interface/linux/_stretch.so
audiostretchy/interface/mac/_stretch.dylib
audiostretchy/interface/win/_stretch.def
audiostretchy/interface/win/_stretch.dll
audiostretchy-1.3.5.dist-info/LICENSE.txt
audiostretchy-1.3.5.dist-info/METADATA
audiostretchy-1.3.5.dist-info/WHEEL
audiostretchy-1.3.5.dist-info/entry_points.txt
audiostretchy-1.3.5.dist-info/top_level.txt
audiostretchy-1.3.5.dist-info/RECORD
