Metadata-Version: 2.1
Name: audiostretchy
Version: 1.3.5
Summary: AudioStretchy is a Python library and CLI tool that which performs fast, high-quality time-stretching of WAV/MP3 files without changing their pitch. Works well for speech, can time-stretch silence separately. AudioStretchy is a wrapper around the audio-stretch C library by David Bryant.
Home-page: https://github.com/twardoch/audiostretchy
Author: Adam Twardoch
Author-email: adam+github@twardoch.com
License: BSD-3-Clause
Project-URL: Documentation, https://pyscaffold.org/
Platform: any
Classifier: Development Status :: 4 - Beta
Classifier: Operating System :: MacOS
Classifier: Operating System :: Microsoft :: Windows
Classifier: Operating System :: POSIX
Classifier: Programming Language :: C
Classifier: Programming Language :: Python
Classifier: Programming Language :: Python :: 3.8
Classifier: Programming Language :: Python :: 3.9
Classifier: Programming Language :: Python :: 3.10
Classifier: Topic :: Multimedia :: Sound/Audio
Classifier: Topic :: Multimedia :: Sound/Audio :: Conversion
Classifier: Topic :: Multimedia :: Sound/Audio :: Speech
Requires-Python: >=3.8
Provides-Extra: all
Provides-Extra: testing
License-File: LICENSE.txt
